{
  "project_info": {
    "project_number": "139025743399",
    "firebase_url": "https://project-1-c6de9.firebaseio.com",
    "project_id": "project-1-c6de9",
    "storage_bucket": "project-1-c6de9.appspot.com"
  },
  "client": [
    {
      "client_info": {
        "mobilesdk_app_id": "1:139025743399:android:e7e0c0af9f35f9a2",
        "android_client_info": {
          "package_name": "com.example.maks.webapp777"
        }
      },
      "oauth_client": [
        {
          "client_id": "139025743399-6osh65av39hkjt4mls1j4otqshb9mu3k.apps.googleusercontent.com",
          "client_type": 3
        }
      ],
      "api_key": [
        {
          "current_key": "AIzaSyDeiAXb2kbWDOacaPykFmpV0nwlMpA4vZ4"
        }
      ],
      "services": {
        "analytics_service": {
          "status": 1
        },
        "appinvite_service": {
          "status": 1,
          "other_platform_oauth_client": []
        },
        "ads_service": {
          "status": 2
        }
      }
    }
  ],
  "configuration_version": "1"
}